{
  "flight_id": "AF448",
  "departure": "CYUL",
  "arrival": "KFLL",
  "route":[
   {
    "fix": "CYUL",
    "distance_km": 30.0,
    "duration_sec": 300,
    "fuel_kg": 11500,
    "speed_samples_kmh": [
      325.4,
      350.3,
      365.6
    ],
    "heading_deg": 230,
    "altitude_ft": 5000,
    "elapsed_time_sec": 300,
    "total_distance": 30.0,
    "speed_kmh": 347.1,
    "temperature": -46,
    "wind": {
      "direction": 270,
      "speed": 75
    },
    "turbulence": "SEVERE",
    "icing": "LIGHT",
    "atc_messages": [
      {
      "at_position": 5,
      "message": {
      "id": "CYUL_UM20",
      "messageRef": "UM20",
      "formattedMessage": "CLIMB TO AND MAINTAIN FL370",
      "direction": "UPLINK",
      "status": "NEW",
      "sender": "ATC1",
      "intent": "Clearance to climb from current altitude to FL370 after departure."
    }}
  ],
  "nearby_airports": [
    {"icao": "CYUL", "name": "Montréal–Trudeau", "descend_to": "FL100", "offset": {"direction": "RIGHT", "distance_nm": 15}, "fuel_kg": 89 },
    {"icao": "CYHU", "name": "St-Hubert", "descend_to": "FL100", "offset": {"direction": "RIGHT", "distance_nm": 15}, "fuel_kg": 171 },
    {"icao": "CYMX", "name": "Montréal–Mirabel", "descend_to": "FL100", "offset": {"direction": "RIGHT", "distance_nm": 15}, "fuel_kg": 193 }
  ]
  },
  {
    "fix": "PTD",
    "distance_km": 127.79,
    "duration_sec": 551,
    "fuel_kg": 11113,
    "speed_samples_kmh": [
      762.9,
      767.8,
      908.0
    ],
    "heading_deg": 228,
    "altitude_ft": 37000,
    "elapsed_time_sec": 851,
    "total_distance": 157.79,
    "speed_kmh": 812.9,
    "temperature": -50,
    "wind": {
      "direction": 270,
      "speed": 60
    },
    "turbulence": "NONE",
    "icing": "LIGHT",
    "atc_messages": [  
      {"at_position": 0,
      "message":{
        "id": "PTD_UM129",
        "messageRef": "UM129",
        "formattedMessage": "REPORT MAINTAINING FL370",
        "direction": "UPLINK",
        "status": "NEW",
        "sender": "ATC3",
        "intent": "Request for a position or level report once the aircraft reaches the cleared flight level."
      }}
    ],
    "nearby_airports":  [
    {"icao": "KABE", "name": "Allentown–Bethlehem", "descend_to": "FL100", "offset": {"direction": "RIGHT", "distance_nm": 15}, "fuel_kg": 67},
    {"icao": "KMDT", "name": "Harrisburg Intl", "descend_to": "FL100", "offset": {"direction": "RIGHT", "distance_nm": 15}, "fuel_kg": 152},
    {"icao": "KAVP", "name": "Wilkes-Barre/Scranton", "descend_to": "FL100", "offset": {"direction": "RIGHT", "distance_nm": 15}, "fuel_kg": 203}
  ]
  },
  {
    "fix": "BOS",
    "distance_km": 118.9,
    "heading_deg": 180,
    "altitude_ft": 37000,
    "duration_sec": 510,
    "elapsed_time_sec": 1361,
    "total_distance": 276.69,
    "fuel_kg": 10950,
    "speed_samples_kmh": [
      750.2,
      760.5,
      820.0
    ],
    "speed_kmh": 777.6,
    "temperature": -52,
    "wind": {
      "direction": 240,
      "speed": 70
    },
    "turbulence": "MODERATE",
    "icing": "TRACE",
    "atc_messages": []
  },
  {
    "fix": "ART",
    "distance_km": 88.9,
    "heading_deg": 187,
    "altitude_ft": 37000,
    "duration_sec": 384,
    "elapsed_time_sec": 935,
    "total_distance": 246.69,
    "fuel_kg": 10662,
    "speed_samples_kmh": [
      753.4,
      759.1,
      829.1
    ],
    "speed_kmh": 780.5,
    "temperature": -52,
    "wind": {
      "direction": 225,
      "speed": 75
    },
    "turbulence": "SEVERE",
    "icing": "LIGHT",
    "atc_messages": [
      {
      "at_position": 0,
      "message": {
        "id": "ART_UM130",
        "messageRef": "UM130",
        "formattedMessage": "REPORT PASSING SYR",
        "direction": "UPLINK",
        "status": "NEW",
        "sender": "ATC2",
        "intent": "Instruction to report when the aircraft has passed the specified position."
    }}
  ],
  "nearby_airports":[
    {"icao": "KART", "name": "Watertown Intl", "descend_to": "FL100", "offset": {"direction": "RIGHT", "distance_nm": 15}, "fuel_kg": 50},
    {"icao": "KGTB", "name": "Wheeler-Sack (Fort Drum)", "descend_to": "FL100", "offset": {"direction": "RIGHT", "distance_nm": 15}, "fuel_kg": 60},
    {"icao": "KRME", "name": "Griffiss (Rome, NY)", "descend_to": "FL100", "offset": {"direction": "RIGHT", "distance_nm": 15}, "fuel_kg": 70}
  ]
  },
  {
    "fix": "SYR",
    "distance_km": 122.23,
    "heading_deg": 211,
    "altitude_ft": 38000,
    "duration_sec": 528,
    "elapsed_time_sec": 1463,
    "total_distance": 368.92,
    "fuel_kg": 10348,
    "speed_samples_kmh": [
      753.7,
      766.9,
      827.0
    ],
    "speed_kmh": 782.5,
    "temperature": -54,
    "wind": {
      "direction": 250,
      "speed": 75
    },
    "turbulence": "NONE",
    "icing": "TRACE",
    "atc_messages": [{
      "at_position": 0,
      "message": {
        "id": "SYR_UM128",
        "messageRef": "UM128",
        "formattedMessage": "DESCEND TO AND MAINTAIN FL370",
        "direction": "UPLINK",
        "status": "NEW",
        "sender": "ATC",
        "intent": "Instruction to descend to a lower flight level."
      }
    }],
    "nearby_airports":[
    {"icao": "KSYR", "name": "Syracuse Hancock", "descend_to": "FL100", "offset": {"direction": "RIGHT", "distance_nm": 15}, "fuel_kg": 80},
    {"icao": "KRME", "name": "Griffiss (Rome, NY)", "descend_to": "FL100", "offset": {"direction": "RIGHT", "distance_nm": 15}, "fuel_kg": 70},
    {"icao": "KITH", "name": "Ithaca Tompkins", "descend_to": "FL100", "offset": {"direction": "RIGHT", "distance_nm": 15}, "fuel_kg": 60}
  ]
  },
  {
    "fix": "CNTER",
    "distance_km": 109.27,
    "heading_deg": 211,
    "altitude_ft": 39000,
    "duration_sec": 473,
    "elapsed_time_sec": 1936,
    "total_distance": 478.19,
    "fuel_kg": 9916,
    "speed_samples_kmh": [
      800.4,
      874.1,
      888.8
    ],
    "speed_kmh": 854.4,
    "temperature": -52,
    "wind": {
      "direction": 250,
      "speed": 95
    },
    "turbulence": "SEVERE",
    "icing": "NONE",
    "atc_messages": [{
      "at_position": 100,
      "message":{
        "id": "CNTER_UM24",
        "messageRef": "UM24",
        "formattedMessage": "DESCEND TO AND MAINTAIN FL370",
        "direction": "UPLINK",
        "status": "NEW",
        "sender": "ATC",
        "intent": "Instruction to descend to a lower flight level."
      }
    }],
    "nearby_airports": [
    {"icao": "KELM", "name": "Elmira/Corning", "descend_to": "FL100", "offset": {"direction": "RIGHT", "distance_nm": 15}, "fuel_kg": 88},
    {"icao": "KBGM", "name": "Binghamton", "descend_to": "FL100", "offset": {"direction": "RIGHT", "distance_nm": 15}, "fuel_kg": 69},
    {"icao": "KAVP", "name": "Wilkes-Barre/Scranton", "descend_to": "FL100", "offset": {"direction": "RIGHT", "distance_nm": 15}, "fuel_kg": 170}
  ]
  },
  {
    "fix": "ZUCCS",
    "distance_km": 59.26,
    "heading_deg": 210,
    "altitude_ft": 37000,
    "duration_sec": 254,
    "elapsed_time_sec": 2190,
    "total_distance": 537.45,
    "fuel_kg": 9529,
    "speed_samples_kmh": [
      770.5,
      875.4,
      890.0
    ],
    "speed_kmh": 845.3,
    "temperature": -46,
    "wind": {
      "direction": 300,
      "speed": 85
    },
    "turbulence": "LIGHT",
    "icing": "NONE",
    "atc_messages": null,
    "nearby_airports":[
    {"icao": "KUNV", "name": "University Park", "descend_to": "FL100", "offset": {"direction": "RIGHT", "distance_nm": 15}, "fuel_kg": 150},
    {"icao": "KIPT", "name": "Williamsport", "descend_to": "FL100", "offset": {"direction": "RIGHT", "distance_nm": 15}, "fuel_kg": 120},
    {"icao": "KSEG", "name": "Penn Valley (Selinsgrove)", "descend_to": "FL100", "offset": {"direction": "RIGHT", "distance_nm": 15}, "fuel_kg": 75}
  ]
  },
  {
    "fix": "PSB",
    "distance_km": 124.08,
    "heading_deg": 219,
    "altitude_ft": 37000,
    "duration_sec": 534,
    "elapsed_time_sec": 2724,
    "total_distance": 661.53,
    "fuel_kg": 9321,
    "speed_samples_kmh": [
      788.0,
      905.9,
      910.1
    ],
    "speed_kmh": 868.0,
    "temperature": -48,
    "wind": {
      "direction": 180,
      "speed": 95
    },
    "turbulence": "SEVERE",
    "icing": "TRACE",
    "atc_messages": null,
    "nearby_airports":[
    {"icao": "KUNV", "name": "University Park", "descend_to": "FL100", "offset": {"direction": "RIGHT", "distance_nm": 15}, "fuel_kg": 150},
    {"icao": "KIPT", "name": "Williamsport", "descend_to": "FL100", "offset": {"direction": "RIGHT", "distance_nm": 15}, "fuel_kg": 120},
    {"icao": "KSEG", "name": "Penn Valley (Selinsgrove)", "descend_to": "FL100", "offset": {"direction": "RIGHT", "distance_nm": 15}, "fuel_kg": 75},
    {"icao": "KIPT", "name": "Williamsport", "descend_to": "FL100", "offset": {"direction": "RIGHT", "distance_nm": 15}, "fuel_kg": 120},
    {"icao": "KMDT", "name": "Harrisburg Intl", "descend_to": "FL100", "offset": {"direction": "RIGHT", "distance_nm": 15}, "fuel_kg": 100}
  ]
  },
  {
    "fix": "GARDN",
    "distance_km": 229.65,
    "heading_deg": 212,
    "altitude_ft": 39000,
    "duration_sec": 992,
    "elapsed_time_sec": 3716,
    "total_distance": 891.18,
    "fuel_kg": 8884,
    "speed_samples_kmh": [
      756.1,
      863.7,
      871.0
    ],
    "speed_kmh": 830.3,
    "temperature": -54,
    "wind": {
      "direction": 180,
      "speed": 60
    },
    "turbulence": "NONE",
    "icing": "MODERATE",
    "atc_messages": [{
      "at_position": 100,
      "message": {
        "id": "GARDN_UM74",
        "messageRef": "UM74",
        "formattedMessage": "PROCEED DIRECT TO OAKLE",
        "direction": "UPLINK",
        "status": "NEW",
        "sender": "ATC",
        "intent": "ATC instructs the aircraft to proceed directly to the specified waypoint, usually for sequencing or approach."
      }
    }],
    "nearby_airports":[
    {"icao": "KIAD", "name": "Washington Dulles", "descend_to": "FL100", "offset": {"direction": "RIGHT", "distance_nm": 15}, "fuel_kg": 150},
    {"icao": "KBWI", "name": "Baltimore/Washington", "descend_to": "FL100", "offset": {"direction": "RIGHT", "distance_nm": 15}, "fuel_kg": 120},
    {"icao": "KDCA", "name": "Washington National", "descend_to": "FL100", "offset": {"direction": "RIGHT", "distance_nm": 15}, "fuel_kg": 100}
  ]
  },
  {
    "fix": "PERRI",
    "distance_km": 20.37,
    "heading_deg": 195,
    "altitude_ft": 37000,
    "duration_sec": 88,
    "elapsed_time_sec": 3804,
    "total_distance": 911.55,
    "fuel_kg": 8072,
    "speed_samples_kmh": [
      769.4,
      858.6,
      866.6
    ],
    "speed_kmh": 831.5,
    "temperature": -52,
    "wind": {
      "direction": 225,
      "speed": 85
    },
    "turbulence": "MODERATE",
    "icing": "TRACE",
    "atc_messages": null,
    "nearby_airports": [
    {"icao": "KRIC", "name": "Richmond Intl", "descend_to": "FL100", "offset": {"direction": "RIGHT", "distance_nm": 15}, "fuel_kg": 150},
    {"icao": "KPHF", "name": "Newport News/Williamsburg", "descend_to": "FL100", "offset": {"direction": "RIGHT", "distance_nm": 15}, "fuel_kg": 120},
    {"icao": "KORF", "name": "Norfolk", "descend_to": "FL100", "offset": {"direction": "RIGHT", "distance_nm": 15}, "fuel_kg": 100}
  ]
  },
  {
    "fix": "OAKLE",
    "distance_km": 33.34,
    "heading_deg": 195,
    "altitude_ft": 37000,
    "duration_sec": 148,
    "elapsed_time_sec": 3952,
    "total_distance": 944.89,
    "fuel_kg": 8000,
    "speed_samples_kmh": [
      731.9,
      735.9,
      885.0
    ],
    "speed_kmh": 784.3,
    "temperature": -52,
    "wind": {
      "direction": 250,
      "speed": 75
    },
    "turbulence": "LIGHT",
    "icing": "MODERATE",
    "atc_messages": null,
    "nearby_airports":[
    {"icao": "KRDU", "name": "Raleigh–Durham", "descend_to": "FL100", "offset": {"direction": "RIGHT", "distance_nm": 15}, "fuel_kg": 109},
    {"icao": "KGSO", "name": "Greensboro/Piedmont Triad", "descend_to": "FL100", "offset": {"direction": "RIGHT", "distance_nm": 15}, "fuel_kg": 166},
    {"icao": "KRWI", "name": "Rocky Mount–Wilson", "descend_to": "FL100", "offset": {"direction": "RIGHT", "distance_nm": 15}, "fuel_kg": 100}
  ]
  },
  {
    "fix": "ASBUR",
    "distance_km": 188.9,
    "heading_deg": 204,
    "altitude_ft": 39000,
    "duration_sec": 817,
    "elapsed_time_sec": 4769,
    "total_distance": 1133.79,
    "fuel_kg": 7879,
    "speed_samples_kmh": [
      764.9,
      808.0,
      819.3
    ],
    "speed_kmh": 797.4,
    "temperature": -50,
    "wind": {
      "direction": 180,
      "speed": 85
    },
    "turbulence": "MODERATE",
    "icing": "LIGHT",
    "atc_messages": null,
    "nearby_airports":[
    {"icao": "KCLT", "name": "Charlotte Douglas", "descend_to": "FL100", "offset": {"direction": "RIGHT", "distance_nm": 15}, "fuel_kg": 206},
    {"icao": "KGSP", "name": "Greenville–Spartanburg", "descend_to": "FL100", "offset": {"direction": "RIGHT", "distance_nm": 15}, "fuel_kg": 166},
    {"icao": "KAVL", "name": "Asheville", "descend_to": "FL100", "offset": {"direction": "RIGHT", "distance_nm": 15}, "fuel_kg": 94}
  ]
  },
  {
    "fix": "MULBE",
    "distance_km": 179.64,
    "heading_deg": 207,
    "altitude_ft": 37000,
    "duration_sec": 776,
    "elapsed_time_sec": 5545,
    "total_distance": 1313.43,
    "fuel_kg": 7210,
    "speed_samples_kmh": [
      842.0,
      869.1,
      885.5
    ],
    "speed_kmh": 865.5,
    "temperature": -46,
    "wind": {
      "direction": 270,
      "speed": 60
    },
    "turbulence": "LIGHT",
    "icing": "LIGHT",
    "atc_messages": null,
    "nearby_airports":[
    {"icao": "KCAE", "name": "Columbia Metro", "descend_to": "FL100", "offset": {"direction": "RIGHT", "distance_nm": 15}, "fuel_kg": 85},
    {"icao": "KAGS", "name": "Augusta", "descend_to": "FL100", "offset": {"direction": "RIGHT", "distance_nm": 15}, "fuel_kg": 49},
    {"icao": "KAHN", "name": "Athens, GA", "descend_to": "FL100", "offset": {"direction": "RIGHT", "distance_nm": 15}, "fuel_kg": 61}
  ]
  },
  {
    "fix": "TIRCO",
    "distance_km": 137.05,
    "heading_deg": 156,
    "altitude_ft": 38000,
    "duration_sec": 595,
    "elapsed_time_sec": 6140,
    "total_distance": 1450.48,
    "fuel_kg": 3538,
    "speed_samples_kmh": [
      881.8,
      904.1,
      908.8
    ],
    "speed_kmh": 898.2,
    "temperature": -54,
    "wind": {
      "direction": 300,
      "speed": 85
    },
    "turbulence": "LIGHT",
    "icing": "TRACE",
    "atc_messages": null,
    "nearby_airports":[
    {"icao": "KJAX", "name": "Jacksonville Intl", "descend_to": "FL100", "offset": {"direction": "RIGHT", "distance_nm": 15}, "fuel_kg": 200},
    {"icao": "KSSI", "name": "Brunswick/Golden Isles", "descend_to": "FL100", "offset": {"direction": "RIGHT", "distance_nm": 15}, "fuel_kg": 150},
    {"icao": "KCRG", "name": "Jacksonville Exec (Craig)", "descend_to": "FL100", "offset": {"direction": "RIGHT", "distance_nm": 15}, "fuel_kg": 100}
  ]
  },
  {
    "fix": "KFLL",
    "distance_km": 0,
    "heading_deg": 170,
    "altitude_ft": 0,
    "duration_sec": 240,
    "elapsed_time_sec": 6380,
    "total_distance": 1470.48,
    "fuel_kg": 3200,
    "speed_samples_kmh": [
      304.0,
      314.0,
      325.8
    ],
    "speed_kmh": 0,
    "temperature": 15,
    "wind": {
      "direction": 0,
      "speed": 0
    },
    "turbulence": "NONE",
    "icing": "NONE",
    "atc_messages": null,
    "nearby_airports": [
    {"icao": "KFLL", "name": "Fort Lauderdale–Hollywood", "descend_to": "FL100", "offset": {"direction": "RIGHT", "distance_nm": 15}, "fuel_kg": 206},
    {"icao": "KMIA", "name": "Miami Intl", "descend_to": "FL100", "offset": {"direction": "RIGHT", "distance_nm": 15}, "fuel_kg": 166},
    {"icao": "KPBI", "name": "Palm Beach Intl", "descend_to": "FL100", "offset": {"direction": "RIGHT", "distance_nm": 15}, "fuel_kg": 94}
  ]
  }
],
  "final_fuel": "3388kg",
  "final_duration": "3:06:45"
}
 